[
    {"name": "v2.2.0", "secondaryName": "v2.2.0_3.8.3+4[gen]","version": "v2.2.0", "checksum": "f17ea224e2fbd05cb849d49e39a7d94393905aa5", "hash": "sha1"},
    {"name": "v3.0.0", "secondaryName": "v3.0.0_3.8.3+4[gen]", "version": "v3.0.0", "checksum": "85c7cb1a16f895bbfa0de33552846c7604921b7b", "hash": "sha1"},
    {"name": "v3.1.0", "secondaryName": "v3.1.0_3.8.3+4[gen]", "version": "v3.1.0", "checksum": "3b90ff8e8e028c6fc9cd74afd4772a4289a34911", "hash": "sha1"},
    {"name": "v3.2.0", "secondaryName": "v3.2.0_3.8.3+4[gen]", "version": "v3.2.0", "checksum": "7ca1ee69db25a24827ccc179a21ec5e20a18e917", "hash": "sha1"},
    {"name": "v3.3.0", "secondaryName": "v3.3.0_3.8.3+4[gen]", "version": "v3.3.0", "checksum": "a77ade730b1cdd84aea9ff05116673630ffd7ae4", "hash": "sha1"},
    {"name": "v3.4.0", "secondaryName": "v3.4.0_3.8.3+4[gen]", "version": "v3.4.0", "checksum": "2b0ba48b31cc6a5f9cb024c6f81c11a986854519", "hash": "sha1"},
    {"name": "v3.4.1", "secondaryName": "v3.4.1_3.8.3+4[gen]", "version": "v3.4.1", "checksum": "21f10cc0e2abb99df84984b05b6f4d6438cadd18", "hash": "sha1"},    
    {"name": "v4.0.1", "secondaryName": "v4.0.1_3.8.3+5[ca35]", "version": "v4.0.1/v4.0.1_3.8.3+5[ca35]", "checksum": "5eee5388f9404e04fc8c0c12d2542e5e6b46a680", "hash": "sha1"},
    {"name": "v4.0.1", "secondaryName": "v4.0.1_3.8.3+5[ca53]", "version": "v4.0.1/v4.0.1_3.8.3+5[ca53]", "checksum": "4339db90ef019045ddf2880b48a0a07d016bc8d7", "hash": "sha1"},
    {"name": "v4.0.1", "secondaryName": "v4.0.1_3.8.3+5[ca55]", "version": "v4.0.1/v4.0.1_3.8.3+5[ca55]", "checksum": "d770dd28210cbabd8d633d054137d242510067c2", "hash": "sha1"},
    {"name": "v4.0.1", "secondaryName": "v4.0.1_3.8.3+5[ca57]", "version": "v4.0.1/v4.0.1_3.8.3+5[ca57]", "checksum": "0222dbf2b244fab325a89ee6facfc18072c61e51", "hash": "sha1"},
    {"name": "v4.0.1", "secondaryName": "v4.0.1_3.8.3+5[ca72]", "version": "v4.0.1/v4.0.1_3.8.3+5[ca72]", "checksum": "c757a7ee612d0d04d082115b964a4414c01f6210", "hash": "sha1"},
    {"name": "v4.0.1", "secondaryName": "v4.0.1_3.8.3+5[ca73]", "version": "v4.0.1/v4.0.1_3.8.3+5[ca73]", "checksum": "b952854efdecf634e5f05ff9c63cf79820ac1a26", "hash": "sha1"},
    {"name": "v4.0.1", "secondaryName": "v4.0.1_3.8.3+5[ca75]", "version": "v4.0.1/v4.0.1_3.8.3+5[ca75]", "checksum": "9762e2f24729c10ad0571009261a3a256f759a5d", "hash": "sha1"},
    {"name": "v4.0.1", "secondaryName": "v4.0.1_3.8.3+5[exm1]", "version": "v4.0.1/v4.0.1_3.8.3+5[exm1]", "checksum": "2bb025be69a8537efef7b2c9558efbabadefc5d2", "hash": "sha1"},
    {"name": "v4.0.1", "secondaryName": "v4.0.1_3.8.3+5[flkr]", "version": "v4.0.1/v4.0.1_3.8.3+5[flkr]", "checksum": "e5fe5a10d90731f891964f40bea4a7081a4ef390", "hash": "sha1"},
    {"name": "v4.0.1", "secondaryName": "v4.0.1_3.8.3+5[saphira]", "version": "v4.0.1/v4.0.1_3.8.3+5[saphira]", "checksum": "05dae5d9736a6e33e2705aa1b088a1942ff50476", "hash": "sha1"},
    {"name": "v4.0.1", "secondaryName": "v4.0.1_3.8.3+5[tx]", "version": "v4.0.1/v4.0.1_3.8.3+5[tx]", "checksum": "fa10ef265342ba9aee32589f3b49696448255a5c", "hash": "sha1"},
    {"name": "v4.0.1", "secondaryName": "v4.0.1_3.8.3+5[gen]", "version": "v4.0.1/v4.0.1_3.8.3+5[gen]", "checksum": "ad9fe481e0eb278f4c6237f78c55337a33e7d5c4", "hash": "sha1"},
    {"name": "v4.2.0", "secondaryName": "v4.2.0_3.8.3+5[ca35]", "version": "v4.2.0/v4.2.0_3.8.3+5[ca35]", "checksum": "ce5d697012cf4404f4c2b17d1419625890042674", "hash": "sha1"},
    {"name": "v4.2.0", "secondaryName": "v4.2.0_3.8.3+5[ca53]", "version": "v4.2.0/v4.2.0_3.8.3+5[ca53]", "checksum": "36d4c6bff59d19c514c63df87a5e965e0b940318", "hash": "sha1"},
    {"name": "v4.2.0", "secondaryName": "v4.2.0_3.8.3+5[ca55]", "version": "v4.2.0/v4.2.0_3.8.3+5[ca55]", "checksum": "68842c61cb0bd113089aa2a31e4bbb1a82c65eff", "hash": "sha1"},
    {"name": "v4.2.0", "secondaryName": "v4.2.0_3.8.3+5[ca57]", "version": "v4.2.0/v4.2.0_3.8.3+5[ca57]", "checksum": "07890f5c530a0ff8eeb3d7b45a0b979f2aa3995e", "hash": "sha1"},
    {"name": "v4.2.0", "secondaryName": "v4.2.0_3.8.3+5[ca72]", "version": "v4.2.0/v4.2.0_3.8.3+5[ca72]", "checksum": "656831b3a8646716ce1f56c6fda98d530e32873c", "hash": "sha1"},
    {"name": "v4.2.0", "secondaryName": "v4.2.0_3.8.3+5[ca73]", "version": "v4.2.0/v4.2.0_3.8.3+5[ca73]", "checksum": "c41e2ceaaa10870d25e729c46ec494ec08a22caf", "hash": "sha1"},
    {"name": "v4.2.0", "secondaryName": "v4.2.0_3.8.3+5[ca75]", "version": "v4.2.0/v4.2.0_3.8.3+5[ca75]", "checksum": "c5e41a620982682bd56ecf4407e66103c6678190", "hash": "sha1"},
    {"name": "v4.2.0", "secondaryName": "v4.2.0_3.8.3+5[exm1]", "version": "v4.2.0/v4.2.0_3.8.3+5[exm1]", "checksum": "dfe7b221ece961d8b1709592054b9f41607ced45", "hash": "sha1"},
    {"name": "v4.2.0", "secondaryName": "v4.2.0_3.8.3+5[flkr]", "version": "v4.2.0/v4.2.0_3.8.3+5[flkr]", "checksum": "1aa0c06ad9ac9eeaccb42ad88da81650b6439eac", "hash": "sha1"},
    {"name": "v4.2.0", "secondaryName": "v4.2.0_3.8.3+5[saphira]", "version": "v4.2.0/v4.2.0_3.8.3+5[saphira]", "checksum": "0a37637fc39be40a59771d8ccfbfe1ec48f6a881", "hash": "sha1"},
    {"name": "v4.2.0", "secondaryName": "v4.2.0_3.8.3+5[tx]", "version": "v4.2.0/v4.2.0_3.8.3+5[tx]", "checksum": "b185deb9b37c1ec1a5baad9587e0ce54a224561a", "hash": "sha1"},
    {"name": "v4.2.0", "secondaryName": "v4.2.0_3.8.3+5[tx2t99]", "version": "v4.2.0/v4.2.0_3.8.3+5[tx2t99]", "checksum": "9d717acc699111ebfe69f2332180eefb48532bcc", "hash": "sha1"},
    {"name": "v4.2.0", "secondaryName": "v4.2.0_3.8.3+5[txt81]", "version": "v4.2.0/v4.2.0_3.8.3+5[txt81]", "checksum": "2971ec949f73a88daf183cdee7e4bfbf4042a0c7", "hash": "sha1"},
    {"name": "v4.2.0", "secondaryName": "v4.2.0_3.8.3+5[txt83]", "version": "v4.2.0/v4.2.0_3.8.3+5[txt83]", "checksum": "84b6b3cdb3be2edb53fc5a33ccdd1a6bc2ebaa72", "hash": "sha1"},
    {"name": "v4.2.0", "secondaryName": "v4.2.0_3.8.3+5[txt88]", "version": "v4.2.0/v4.2.0_3.8.3+5[txt88]", "checksum": "dc1016975a71ddc8d261f44ceb19982a538030ab", "hash": "sha1"},
    {"name": "v4.2.0", "secondaryName": "v4.2.0_3.8.3+5[gen]", "version": "v4.2.0/v4.2.0_3.8.3+5[gen]", "checksum": "438fce3bfcbe8d28d0c29838dbea0f80fc1b594d", "hash": "sha1"},
    {"name": "v5.0.0", "secondaryName": "v5.0.0_3.8.3+7[ca35]", "version": "v5.0.0/v5.0.0_3.8.3+7[ca35]", "checksum": "0d15e553cc21d6aa63235338b72bc9947bbb4202", "hash": "sha1"},
    {"name": "v5.0.0", "secondaryName": "v5.0.0_3.8.3+7[ca53]", "version": "v5.0.0/v5.0.0_3.8.3+7[ca53]", "checksum": "386e8a45f7d5ef353b31216afc1be659e361f062", "hash": "sha1"},
    {"name": "v5.0.0", "secondaryName": "v5.0.0_3.8.3+7[ca55]", "version": "v5.0.0/v5.0.0_3.8.3+7[ca55]", "checksum": "fbb5be9d7cf02d5ee2032361acbd47b007cb16d8", "hash": "sha1"},
    {"name": "v5.0.0", "secondaryName": "v5.0.0_3.8.3+7[ca57]", "version": "v5.0.0/v5.0.0_3.8.3+7[ca57]", "checksum": "350220eab9e620ec49588370d99a60d23ff54c85", "hash": "sha1"},
    {"name": "v5.0.0", "secondaryName": "v5.0.0_3.8.3+7[ca72]", "version": "v5.0.0/v5.0.0_3.8.3+7[ca72]", "checksum": "edbb3b73d238ce144edc1d28ac987d3bbad011fb", "hash": "sha1"},
    {"name": "v5.0.0", "secondaryName": "v5.0.0_3.8.3+7[ca73]", "version": "v5.0.0/v5.0.0_3.8.3+7[ca73]", "checksum": "6eec3deea8039007e781ff7e68ac18f434eb405f", "hash": "sha1"},
    {"name": "v5.0.0", "secondaryName": "v5.0.0_3.8.3+7[ca75]", "version": "v5.0.0/v5.0.0_3.8.3+7[ca75]", "checksum": "420da2af5e9e5677e5252a13c8bce36c8b9886ca", "hash": "sha1"},
    {"name": "v5.0.0", "secondaryName": "v5.0.0_3.8.3+7[exm1]", "version": "v5.0.0/v5.0.0_3.8.3+7[exm1]", "checksum": "ed74bb6eb2ca5125af8aacb6b7a7bbc45e40ffd2", "hash": "sha1"},
    {"name": "v5.0.0", "secondaryName": "v5.0.0_3.8.3+7[flkr]", "version": "v5.0.0/v5.0.0_3.8.3+7[flkr]", "checksum": "0ae9aa3a7e75c44491a2294ad41faaff0a0c304a", "hash": "sha1"},
    {"name": "v5.0.0", "secondaryName": "v5.0.0_3.8.3+7[gen]", "version": "v5.0.0/v5.0.0_3.8.3+7[gen]", "checksum": "fb40f3423da7889462249072b1690cea85f99d87", "hash": "sha1"},
    {"name": "v5.0.0", "secondaryName": "v5.0.0_3.8.3+7[saphira]", "version": "v5.0.0/v5.0.0_3.8.3+7[saphira]", "checksum": "a6c8116940d447761ebc6af57db8e32bfaa3ffaa", "hash": "sha1"},
    {"name": "v5.0.0", "secondaryName": "v5.0.0_3.8.3+7[tx]", "version": "v5.0.0/v5.0.0_3.8.3+7[tx]", "checksum": "5011892e0b6a0c169c78d7a185fb968474f4f25d", "hash": "sha1"},
    {"name": "v5.0.0", "secondaryName": "v5.0.0_3.8.3+7[tx2t99]", "version": "v5.0.0/v5.0.0_3.8.3+7[tx2t99]", "checksum": "fe322862847d07435b336d80a20af7c9270485ce", "hash": "sha1"},
    {"name": "v5.0.0", "secondaryName": "v5.0.0_3.8.3+7[txt81]", "version": "v5.0.0/v5.0.0_3.8.3+7[txt81]", "checksum": "7152ff30cf3cad4ee37c2d313db36b82afd7ed7b", "hash": "sha1"},
    {"name": "v5.0.0", "secondaryName": "v5.0.0_3.8.3+7[txt83]", "version": "v5.0.0/v5.0.0_3.8.3+7[txt83]", "checksum": "a4a4c5389cb1318ccf07ce5aaa708f68ee480425", "hash": "sha1"},
    {"name": "v5.0.0", "secondaryName": "v5.0.0_3.8.3+7[txt88]", "version": "v5.0.0/v5.0.0_3.8.3+7[txt88]", "checksum": "10e140427b1b8d05cc50a6abaaac54c724212bb0", "hash": "sha1"}
]